MANIFEST.in
VERSION
setup.py
oauthx/__init__.py
oauthx/package.json
oauthx/providercache.py
oauthx.egg-info/PKG-INFO
oauthx.egg-info/SOURCES.txt
oauthx.egg-info/dependency_links.txt
oauthx.egg-info/requires.txt
oauthx.egg-info/top_level.txt
oauthx/models/__init__.py
oauthx/models/baseclient.py
oauthx/models/client.py
oauthx/models/confidentialclient.py
oauthx/models/lazyservermetadata.py
oauthx/models/provider.py
oauthx/models/publicclient.py
oauthx/models/servermetadata.py
oauthx/server/__init__.py
oauthx/server/__main__.py
oauthx/server/basestorage.py
oauthx/server/oidcroutehandler.py
oauthx/server/oidcrouter.py
oauthx/server/config/__init__.py
oauthx/server/config/config.py
oauthx/server/config/implementationconfig.py
oauthx/server/config/issuerconfig.py
oauthx/server/models/__init__.py
oauthx/server/models/application.py
oauthx/server/models/authorizationrequest.py
oauthx/server/models/authorizationstate.py
oauthx/server/params/__init__.py
oauthx/server/params/currentauthorizationrequest.py
oauthx/server/params/currentconfig.py
oauthx/server/ref/__init__.py
oauthx/server/ref/storage.py
oauthx/server/ref/subject.py
oauthx/server/ref/template.py
oauthx/server/ref/templates/oauth/base.html.j2
oauthx/server/ref/templates/oauth/error.html.j2
oauthx/server/types/__init__.py
oauthx/server/types/irequestsubject.py
oauthx/server/types/iserverstorage.py
oauthx/server/types/request.py
oauthx/types/__init__.py
oauthx/types/authorizationcodegrant.py
oauthx/types/authorizationrequest.py
oauthx/types/authorizationrequestobject.py
oauthx/types/authorizationrequestparameters.py
oauthx/types/authorizationrequestreference.py
oauthx/types/authorizedgrant.py
oauthx/types/baseauthorizationrequest.py
oauthx/types/basegrant.py
oauthx/types/clientassertiontype.py
oauthx/types/clientauthenticationmethod.py
oauthx/types/endpointerror.py
oauthx/types/endpointerrortype.py
oauthx/types/error.py
oauthx/types/fatalerror.py
oauthx/types/grant.py
oauthx/types/granttype.py
oauthx/types/invalidrequest.py
oauthx/types/pckechallengemethod.py
oauthx/types/redirecturi.py
oauthx/types/refreshtokengrant.py
oauthx/types/requesturi.py
